Single_Float_Adder/Float_Add.v
module Float_Add(clk,rst,start,X,Y,valid,sum);

input clk;
input rst;
input start;
input [31:0]X,Y;	//In IEEE754 format
output [31:0]sum;	//In IEEE754 format
output valid;

reg X_sign;
reg Y_sign;
reg sum_sign,next_sum_sign;
reg [7:0] X_exp;
reg [7:0] Y_exp;
reg [7:0] sum_exp,next_sum_exp;
reg [23:0] X_mant, Y_mant;
reg [23:0] X_mantissa, Y_mantissa; //24 bits = 23 + implicit 1
reg [24:0] sum_mantissa, next_sum_mantissa; //sum is 25 bits

reg [8:0] expsub,abs_diff;
reg [24:0] sum_mantissa_temp;
reg [1:0] next_state, pres_state;
reg valid, next_valid;

parameter IDLE = 2'b00;
parameter START = 2'b01;
parameter SHIFT_MANT = 2'b10;

assign sum = {sum_sign,sum_exp,sum_mantissa[22:0]};
assign add_carry = sum_mantissa[24] & !(X_sign ^ Y_sign);	//carry during add
assign sub_borrow = sum_mantissa_temp[24] & (X_sign ^ Y_sign); //borrow during sub

always @ (posedge clk or negedge rst)
begin
if(!rst)
begin
	valid 	     <= 1'b0;
	pres_state   <= 2'd0;
	sum_exp      <= 8'd0;
	sum_mantissa <= 25'd0;
	sum_sign     <= 1'b0;
end
else
begin
	valid 	     <= next_valid;
	pres_state   <= next_state;
	sum_exp      <= next_sum_exp;
	sum_mantissa <= next_sum_mantissa;
	sum_sign     <= next_sum_sign;
end
end

always @ (*)
begin 
next_valid = 1'b0;
X_sign = X[31];
X_exp = X[30:23];
X_mant = {1'b1,X[22:0]};	
Y_sign = Y[31];
Y_exp = Y[30:23];
Y_mant = {1'b1,Y[22:0]};
next_sum_sign = sum_sign;		
next_sum_exp = 8'd0;
next_sum_mantissa = 25'd0;
next_state = IDLE;
sum_mantissa_temp = 25'd0;

case(pres_state)
IDLE:
begin
	next_valid = 1'b0;
	X_sign = X[31];
	X_exp = X[30:23];
	X_mant = {1'b1,X[22:0]};	//Implicit 1 added
	Y_sign = Y[31];
	Y_exp = Y[30:23];
	Y_mant = {1'b1,Y[22:0]};
	next_sum_sign = 1'b0;
	next_sum_exp = 8'd0;
	next_sum_mantissa = 25'd0;
	next_state = (start) ? START : pres_state;
end

START:
begin
    expsub = X_exp - Y_exp;
    abs_diff = expsub[8] ? !(expsub[7:0])+1'b1 : expsub[7:0];	//Absolute difference
    X_mantissa = expsub[8] ? X_mant >> abs_diff : X_mant;	//X mant shifts if expsub[8]
    Y_mantissa = expsub[8] ? Y_mant : Y_mant >> abs_diff;   //Y mant shifts if !expsub[8]
    next_sum_exp = expsub[8] ? Y_exp : X_exp;			//Greater exp taken
    sum_mantissa_temp = !(X_sign ^ Y_sign) ? X_mantissa + Y_mantissa :	//Add mantissas
			 (X_sign) ? Y_mantissa - X_mantissa :
			 (Y_sign) ? X_mantissa - Y_mantissa : sum_mantissa;
    next_sum_mantissa = (sub_borrow) ? ~(sum_mantissa_temp)+1'b1 : sum_mantissa_temp; //2s comp if req
    next_sum_sign = ((X_sign & Y_sign) || sub_borrow);
    next_valid = 1'b0;	
    next_state = SHIFT_MANT;	
end

SHIFT_MANT:					//State to shift Mantissa to make bit23 = 1
begin
    next_sum_exp = sum_mantissa[23] ? sum_exp : (add_carry)? sum_exp + 1'b1 : sum_exp - 1'b1;
    next_sum_mantissa = sum_mantissa[23] ? sum_mantissa : (add_carry) ? sum_mantissa >> 1 : sum_mantissa << 1;
    next_valid = sum_mantissa[23] ? 1'b1 : 1'b0;
    next_state = sum_mantissa[23] ? IDLE : pres_state;
end

endcase
end
endmodule

Single_Float_Adder/Float_Add_tb.v
`timescale 1ns/1ps
`include "Float_Add.v"
module Float_Add_tb;

reg clk,rst,start;
reg [31:0]X,Y;
wire [31:0]sum;
wire valid;

always #5 clk = ~clk;

Float_Add inst (clk,rst,start,X,Y,valid,sum);


initial
begin
//X=32'h40d80000; Y=32'hc0700000;	//6.75,-3.75
//X=32'hc0d80000; Y=32'h40700000;	//-6.75,3.75
X=32'h40700000; Y=32'hc0d80000;	        //3.75,-6.75
//X=32'hc0700000; Y=32'h40d80000;	//-3.75,6.75
clk=1'b1; rst=1'b0; start=1'b0;
#10 rst = 1'b1;
#10 start = 1'b1;
#10 start = 1'b0;
@valid
#10 X=32'b00111111100111110111110011101110; //1.246
Y=32'b01000001001001110011001100110011; //10.45
//#10 X=32'hc0d80000; Y=32'hc0700000;    //-6.75,-3.75
start = 1'b1;
#10 start = 1'b0;

end      
initial 
begin
$dumpfile("float_add.vcd");
$dumpvars(0,Float_Add_tb);
$monitor($time,"X=%d, Y=%d, sum=%d ",X,Y,sum);
#200 $finish;
end

endmodule

Single_Float_Adder/float_add.vcd
$date
	Tue Nov 28 23:04:16 2023
$end
$version
	Icarus Verilog
$end
$timescale
	1ps
$end
$scope module Float_Add_tb $end
$var wire 1 ! valid $end
$var wire 32 " sum [31:0] $end
$var reg 32 # X [31:0] $end
$var reg 32 $ Y [31:0] $end
$var reg 1 % clk $end
$var reg 1 & rst $end
$var reg 1 ' start $end
$scope module inst $end
$var wire 32 ( X [31:0] $end
$var wire 32 ) Y [31:0] $end
$var wire 1 * add_carry $end
$var wire 1 % clk $end
$var wire 1 & rst $end
$var wire 1 ' start $end
$var wire 1 + sub_borrow $end
$var wire 32 , sum [31:0] $end
$var parameter 2 - IDLE $end
$var parameter 2 . SHIFT_MANT $end
$var parameter 2 / START $end
$var reg 8 0 X_exp [7:0] $end
$var reg 24 1 X_mant [23:0] $end
$var reg 24 2 X_mantissa [23:0] $end
$var reg 1 3 X_sign $end
$var reg 8 4 Y_exp [7:0] $end
$var reg 24 5 Y_mant [23:0] $end
$var reg 24 6 Y_mantissa [23:0] $end
$var reg 1 7 Y_sign $end
$var reg 9 8 abs_diff [8:0] $end
$var reg 9 9 expsub [8:0] $end
$var reg 2 : next_state [1:0] $end
$var reg 8 ; next_sum_exp [7:0] $end
$var reg 25 < next_sum_mantissa [24:0] $end
$var reg 1 = next_sum_sign $end
$var reg 1 > next_valid $end
$var reg 2 ? pres_state [1:0] $end
$var reg 8 @ sum_exp [7:0] $end
$var reg 25 A sum_mantissa [24:0] $end
$var reg 25 B sum_mantissa_temp [24:0] $end
$var reg 1 C sum_sign $end
$var reg 1 ! valid $end
$upscope $end
$upscope $end
$enddefinitions $end
$comment Show the parameter values. $end
$dumpall
b1 /
b10 .
b0 -
$end
#0
$dumpvars
0C
b0 B
b0 A
b0 @
b0 ?
0>
0=
b0 <
b0 ;
b0 :
bx 9
bx 8
17
bx 6
b110110000000000000000000 5
b10000001 4
03
bx 2
b111100000000000000000000 1
b10000000 0
b0 ,
0+
0*
b11000000110110000000000000000000 )
b1000000011100000000000000000000 (
0'
0&
1%
b11000000110110000000000000000000 $
b1000000011100000000000000000000 #
b0 "
0!
$end
#5000
0%
#10000
1%
1&
#15000
0%
#20000
1=
1+
b11000000000000000000000 <
b1101000000000000000000000 B
b10000001 ;
b110110000000000000000000 6
b11110000000000000000000 2
b1 8
b111111111 9
b1 ?
b10 :
1%
1'
#25000
0%
#30000
0+
1C
b11000000000000000000000 A
b11000000111000000000000000000000 "
b11000000111000000000000000000000 ,
b10000001 @
b10 ?
b0 B
b10 :
b110000000000000000000000 <
b10000000 ;
1=
1%
0'
#35000
0%
#40000
1>
b0 :
b110000000000000000000000 <
b10000000 ;
b110000000000000000000000 A
b11000000010000000000000000000000 "
b11000000010000000000000000000000 ,
b10000000 @
1%
#45000
0%
#50000
0=
b0 <
b0 ;
0>
b0 ?
1!
1%
#55000
0%
#60000
b111101101111000110101010 <
b111101101111000110101010 B
b10000010 ;
b101001110011001100110011 6
b10011111011111001110111 2
b111111101 9
0C
b0 A
b0 "
b0 ,
b0 @
b1 ?
0!
b10 :
0=
b101001110011001100110011 5
b10000010 4
07
b100111110111110011101110 1
b1111111 0
1%
1'
b1000001001001110011001100110011 $
b1000001001001110011001100110011 )
b111111100111110111110011101110 #
b111111100111110111110011101110 (
#65000
0%
#70000
1>
b111101101111000110101010 A
b1000001011101101111000110101010 "
b1000001011101101111000110101010 ,
b10000010 @
b10 ?
b0 B
b0 :
b111101101111000110101010 <
b10000010 ;
1%
0'
#75000
0%
#80000
b0 <
b0 ;
0>
b0 ?
1!
1%
#85000
0%
#90000
b0 A
b0 "
b0 ,
b0 @
0!
1%
