Single_Float_Adder/single_float_adder.v
module single_float_adder #(parameter DWIDTH=32,EXPONENT_WIDTH=8,BIAS=8'd127)(input [DWIDTH-1:0]a,b,input ip_ready,rst,clk,output reg valid, output [DWIDTH-1:0]sum);

reg a_sign,b_sign;
reg [EXPONENT_WIDTH-1:0] a_exp,b_exp;
reg [DWIDTH-EXPONENT_WIDTH-1:0] a_mantissa,b_mantissa;	// Extract sign, exponent and mantissa information from input

reg [EXPONENT_WIDTH:0] sub_exp;
reg [EXPONENT_WIDTH-1:0] abs_diff;
reg [DWIDTH-EXPONENT_WIDTH:0] sum_mantissa_add_sub;					
reg [DWIDTH-EXPONENT_WIDTH-1:0] a_mantissa_shift,b_mantissa_shift;	// reg for operation 
reg final_sign,next_sign;															
reg [EXPONENT_WIDTH-1:0] final_exp,next_exp;
reg [DWIDTH-EXPONENT_WIDTH:0] final_mantissa,next_mantissa;
reg valid_sig;
reg [1:0] PS,NS;

parameter IDLE=2'b00;
parameter ADD=2'b01;
parameter NORMALIZE=2'b10;

wire sub_borrow,sum_carry;
/*wire [DWIDTH-1:0] sum_1st;
wire [DWIDTH:0] sp_fp_add_1st,sp_fp_add_2nd;
reg exp_equal;

assign sum_1st={final_sign,final_exp,final_mantissa[DWIDTH-EXPONENT_WIDTH-2:0]};
assign sp_fp_add_1st=a-b;
assign sp_fp_add_2nd=(sp_fp_add_1st[DWIDTH])?~(sp_fp_add_1st)+1'b1:sp_fp_add_1st;

assign sum=(exp_equal)?sp_fp_add_2nd[DWIDTH-1:0]:sum_1st;
*/
assign sum= {final_sign,final_exp,final_mantissa[22:0]};
assign sub_borrow = sum_mantissa_add_sub[24] & (a_sign ^ b_sign);	//borrow during sub
assign sum_carry = next_mantissa[24] & !(a_sign^b_sign);
/*
always @ (*)
begin
	if(a_exp==b_exp)
		exp_equal=1;
	else
		exp_equal=0;
end
*/
always@(posedge clk)
begin
	if(rst)
		begin
			final_exp<=0;
			final_sign<=0;
			final_mantissa<=0;
			valid<=0;
			PS<= 0;
		end
	else
		begin
			PS<=NS;
			final_exp<= next_exp;
			final_sign <= next_sign;
			final_mantissa<= next_mantissa;
			valid <= valid_sig;
		end
end

always @(*)
begin
sub_exp=0;
abs_diff=0;
a_mantissa_shift=0;
b_mantissa_shift=0;
next_exp=0;
sum_mantissa_add_sub=0;
next_mantissa=0;
next_sign=0;
NS=IDLE;

case(PS)
IDLE:begin
		a_sign=a[DWIDTH-1];
		b_sign=b[DWIDTH-1];
		a_exp=a[DWIDTH-2:DWIDTH-EXPONENT_WIDTH-1];			//assiging sign bit, exponent and mantissa values
		b_exp=b[DWIDTH-2:DWIDTH-EXPONENT_WIDTH-1];
		a_mantissa={1'b1,a[DWIDTH-EXPONENT_WIDTH-2:0]};
		b_mantissa={1'b1,b[DWIDTH-EXPONENT_WIDTH-2:0]};
		valid_sig=0;
		NS=(ip_ready)?ADD:IDLE;
	end
ADD:begin
		sub_exp =  a_exp-b_exp;				//calculate diff between two exponent
		abs_diff = sub_exp[EXPONENT_WIDTH]?~(sub_exp[EXPONENT_WIDTH-1:0])+1'b1:sub_exp[EXPONENT_WIDTH-1:0];	//take absoulte value of difference
		a_mantissa_shift = sub_exp[EXPONENT_WIDTH]?a_mantissa >> abs_diff: a_mantissa;		//shift mantissa by abs exponet diff of whose exponent is smaller 
		b_mantissa_shift = sub_exp[EXPONENT_WIDTH]?b_mantissa : b_mantissa >> abs_diff;
		next_exp = sub_exp[EXPONENT_WIDTH] ? b_exp:a_exp;			//final exponent is value whose exponent is greater
		sum_mantissa_add_sub=!(a_sign^b_sign)?a_mantissa_shift+b_mantissa_shift:(a_sign)?b_mantissa_shift-a_mantissa_shift:(b_sign)?a_mantissa_shift-b_mantissa_shift:0; //add or subtract mantissa values based on sign bit
		next_mantissa=(sub_borrow) ? ~(sum_mantissa_add_sub)+1'b1 : sum_mantissa_add_sub;	//take 2s complement if borrow occur during mantissa subtraction
		next_sign = ((a_sign & b_sign) || sub_borrow);	//final sign of output
		valid_sig=0;
		NS=NORMALIZE;
	end
NORMALIZE:begin
			next_exp= final_mantissa[23]? final_exp:(sum_carry)? final_exp+1'b1:final_exp-1'b1;
			next_mantissa=final_mantissa[23]?final_mantissa:(sum_carry)?final_mantissa>>1:final_mantissa<<1;
			valid_sig=final_mantissa[23]?1:0;
			NS = final_mantissa[23]?IDLE:NORMALIZE;
		end
endcase
end
endmodule

Single_Float_Adder/single_float_adder_tb.v
`timescale 1ns/1ps
`include "single_float_adder.v"
module single_float_adder_tb;

reg clk,rst;
reg [31:0]X,Y;
reg ip_ready;
wire [31:0]sum;
wire valid;

always #5 clk = ~clk;

single_float_adder #(.DWIDTH(32),.EXPONENT_WIDTH(8),.BIAS(127)) dut (.clk(clk),.rst(rst),.a(X),.b(Y),.ip_ready(ip_ready),.sum(sum),.valid(valid));


initial
begin
clk=0; 
rst=1;
#7 rst=0; ip_ready=1'b1;
X=32'b00111111010011001100110011001101;
Y=32'b10111111000000000000000000000000;
@(valid)
ip_ready=1'b0;
#7 X=32'b00111111100111110111110011101110; //1.246
Y=32'b01000001001001110011001100110011; //10.45
#7  ip_ready=1'b1;


end      
initial 
begin
$dumpfile("single_float_add.vcd");
$dumpvars(0,single_float_adder_tb);
$monitor($time,"X=%d, Y=%d, sum=%d ",X,Y,sum);
#200 $finish;
end

endmodule

Single_Float_Adder/single_float_add.vcd
$date
	Tue Nov 28 23:18:29 2023
$end
$version
	Icarus Verilog
$end
$timescale
	1ps
$end
$scope module single_float_adder_tb $end
$var wire 1 ! valid $end
$var wire 32 " sum [31:0] $end
$var reg 32 # X [31:0] $end
$var reg 32 $ Y [31:0] $end
$var reg 1 % clk $end
$var reg 1 & ip_ready $end
$var reg 1 ' rst $end
$scope module dut $end
$var wire 32 ( a [31:0] $end
$var wire 32 ) b [31:0] $end
$var wire 1 % clk $end
$var wire 1 & ip_ready $end
$var wire 1 ' rst $end
$var wire 1 * sub_borrow $end
$var wire 1 + sum_carry $end
$var wire 32 , sum [31:0] $end
$var parameter 2 - ADD $end
$var parameter 32 . BIAS $end
$var parameter 32 / DWIDTH $end
$var parameter 32 0 EXPONENT_WIDTH $end
$var parameter 2 1 IDLE $end
$var parameter 2 2 NORMALIZE $end
$var reg 2 3 NS [1:0] $end
$var reg 2 4 PS [1:0] $end
$var reg 8 5 a_exp [7:0] $end
$var reg 24 6 a_mantissa [23:0] $end
$var reg 24 7 a_mantissa_shift [23:0] $end
$var reg 1 8 a_sign $end
$var reg 8 9 abs_diff [7:0] $end
$var reg 8 : b_exp [7:0] $end
$var reg 24 ; b_mantissa [23:0] $end
$var reg 24 < b_mantissa_shift [23:0] $end
$var reg 1 = b_sign $end
$var reg 8 > final_exp [7:0] $end
$var reg 25 ? final_mantissa [24:0] $end
$var reg 1 @ final_sign $end
$var reg 8 A next_exp [7:0] $end
$var reg 25 B next_mantissa [24:0] $end
$var reg 1 C next_sign $end
$var reg 9 D sub_exp [8:0] $end
$var reg 25 E sum_mantissa_add_sub [24:0] $end
$var reg 1 ! valid $end
$var reg 1 F valid_sig $end
$upscope $end
$upscope $end
$enddefinitions $end
$comment Show the parameter values. $end
$dumpall
b10 2
b0 1
b1000 0
b100000 /
b1111111 .
b1 -
$end
#0
$dumpvars
xF
bx E
bx D
xC
bx B
bx A
x@
bx ?
bx >
x=
bx <
bx ;
bx :
bx 9
x8
bx 7
bx 6
bx 5
bx 4
bx 3
bx ,
x+
x*
bx )
bx (
1'
x&
0%
bx $
bx #
bx "
x!
$end
#5000
0+
0*
0F
b1xxxxxxxxxxxxxxxxxxxxxxx ;
b1xxxxxxxxxxxxxxxxxxxxxxx 6
b0x 3
0C
b0 B
b0 E
b0 A
b0 <
b0 7
b0 9
b0 D
b0 4
0!
b0 ?
0@
b0 "
b0 ,
b0 >
1%
#7000
b100000000000000000000000 ;
b110011001100110011001101 6
b1111110 :
b1111110 5
1=
08
b1 3
b10111111000000000000000000000000 $
b10111111000000000000000000000000 )
b111111010011001100110011001101 #
b111111010011001100110011001101 (
1&
0'
#10000
0%
#15000
b10011001100110011001101 B
b10011001100110011001101 E
b1111110 A
b100000000000000000000000 <
b110011001100110011001101 7
b10 3
b1 4
1%
#20000
0%
#25000
b10 3
b100110011001100110011010 B
b0 E
b1111101 A
b0 <
b0 7
b10011001100110011001101 ?
b111111010011001100110011001101 "
b111111010011001100110011001101 ,
b1111110 >
b10 4
1%
#30000
0%
#35000
1F
b0 3
b100110011001100110011010 B
b1111101 A
b100110011001100110011010 ?
b111110100110011001100110011010 "
b111110100110011001100110011010 ,
b1111101 >
1%
#40000
0%
#45000
0&
b0 3
0F
b0 B
b0 A
1!
b0 4
1%
#50000
0%
#52000
b101001110011001100110011 ;
b100111110111110011101110 6
b10000010 :
b1111111 5
0=
b1000001001001110011001100110011 $
b1000001001001110011001100110011 )
b111111100111110111110011101110 #
b111111100111110111110011101110 (
#55000
0!
b0 ?
b0 "
b0 ,
b0 >
1%
#59000
b1 3
1&
#60000
0%
#65000
b101110110010001011010000 B
b101110110010001011010000 E
b10000010 A
b101001110011001100110011 <
b100111110111110011101 7
b11 9
b111111101 D
b10 3
b1 4
1%
#70000
0%
#75000
1F
b0 3
b101110110010001011010000 B
b0 E
b10000010 A
b0 <
b0 7
b0 9
b0 D
b101110110010001011010000 ?
b1000001001110110010001011010000 "
b1000001001110110010001011010000 ,
b10000010 >
b10 4
1%
#80000
0%
#85000
b1 3
0F
b0 B
b0 A
1!
b0 4
1%
#90000
0%
#95000
b101110110010001011010000 B
b101110110010001011010000 E
b10000010 A
b101001110011001100110011 <
b100111110111110011101 7
b11 9
b111111101 D
b10 3
0!
b0 ?
b0 "
b0 ,
b0 >
b1 4
1%
#100000
0%
#105000
1F
b0 3
b101110110010001011010000 B
b0 E
b10000010 A
b0 <
b0 7
b0 9
b0 D
b101110110010001011010000 ?
b1000001001110110010001011010000 "
b1000001001110110010001011010000 ,
b10000010 >
b10 4
1%
#110000
0%
#115000
b1 3
0F
b0 B
b0 A
1!
b0 4
1%
#120000
0%
#125000
b101110110010001011010000 B
b101110110010001011010000 E
b10000010 A
b101001110011001100110011 <
b100111110111110011101 7
b11 9
b111111101 D
b10 3
0!
b0 ?
b0 "
b0 ,
b0 >
b1 4
1%
#130000
0%
#135000
1F
b0 3
b101110110010001011010000 B
b0 E
b10000010 A
b0 <
b0 7
b0 9
b0 D
b101110110010001011010000 ?
b1000001001110110010001011010000 "
b1000001001110110010001011010000 ,
b10000010 >
b10 4
1%
#140000
0%
#145000
b1 3
0F
b0 B
b0 A
1!
b0 4
1%
#150000
0%
#155000
b101110110010001011010000 B
b101110110010001011010000 E
b10000010 A
b101001110011001100110011 <
b100111110111110011101 7
b11 9
b111111101 D
b10 3
0!
b0 ?
b0 "
b0 ,
b0 >
b1 4
1%
#160000
0%
#165000
1F
b0 3
b101110110010001011010000 B
b0 E
b10000010 A
b0 <
b0 7
b0 9
b0 D
b101110110010001011010000 ?
b1000001001110110010001011010000 "
b1000001001110110010001011010000 ,
b10000010 >
b10 4
1%
#170000
0%
#175000
b1 3
0F
b0 B
b0 A
1!
b0 4
1%
#180000
0%
#185000
b101110110010001011010000 B
b101110110010001011010000 E
b10000010 A
b101001110011001100110011 <
b100111110111110011101 7
b11 9
b111111101 D
b10 3
0!
b0 ?
b0 "
b0 ,
b0 >
b1 4
1%
#190000
0%
#195000
1F
b0 3
b101110110010001011010000 B
b0 E
b10000010 A
b0 <
b0 7
b0 9
b0 D
b101110110010001011010000 ?
b1000001001110110010001011010000 "
b1000001001110110010001011010000 ,
b10000010 >
b10 4
1%
